[
	{
		"வரிசை எண்": "01",
		"தலப் பெயர்": "திருவதிகை வீரட்டானம்",
		"பதிக எண்": "4.001",
		"பாடல்": "கூற்றாயின வாறுவி"
	},
	{
		"வரிசை எண்": "02",
		"தலப் பெயர்": "பொது - மறுமாற்றம்",
		"பதிக எண்": "6.098",
		"பாடல்": "நாமார்க்குங் குடியல்லோம்"
	},
	{
		"வரிசை எண்": "03",
		"தலப் பெயர்": "தனித் திருக்குறுந்தொகை",
		"பதிக எண்": "5.090",
		"பாடல்": "மாசில் வீணையும்"
	},
	{
		"வரிசை எண்": "04",
		"தலப் பெயர்": "திருவதிகை வீரட்டானம்",
		"பதிக எண்": "4.002",
		"பாடல்": "சுண்ணவெண் சந்தனச்"
	},
	{
		"வரிசை எண்": "05",
		"தலப் பெயர்": "பொது - நமசிவாயத் திருப்பதிகம்",
		"பதிக எண்": "4.011",
		"பாடல்": "சொற்றுணை வேதியன்"
	},
	{
		"வரிசை எண்": "06",
		"தலப் பெயர்": "திருப்பாதிப்புலியூர்",
		"பதிக எண்": "4.094",
		"பாடல்": "ஈன்றாளு மாயெனக்"
	},
	{
		"வரிசை எண்": "07",
		"தலப் பெயர்": "திருவதிகை வீரட்டானம்",
		"பதிக எண்": "6.003",
		"பாடல்": "வெறிவிரவு கூவிளநற்"
	},
	{
		"வரிசை எண்": "08",
		"தலப் பெயர்": "திருவதிகை வீரட்டானம்",
		"பதிக எண்": "4.010",
		"பாடல்": "முளைக்கதிரி ளம்பிறை"
	},
	{
		"வரிசை எண்": "09",
		"தலப் பெயர்": "திருவதிகை வீரட்டானம்",
		"பதிக எண்": "4.024",
		"பாடல்": "இரும்புகொப் பளித்த"
	},
	{
		"வரிசை எண்": "10",
		"தலப் பெயர்": "திருவதிகை வீரட்டானம்",
		"பதிக எண்": "4.025",
		"பாடல்": "வெண்ணிலா மதியந்"
	},
	{
		"வரிசை எண்": "11",
		"தலப் பெயர்": "திருவதிகை வீரட்டானம்",
		"பதிக எண்": "4.026",
		"பாடல்": "நம்பனே எங்கள்"
	},
	{
		"வரிசை எண்": "12",
		"தலப் பெயர்": "திருவதிகை வீரட்டானம்",
		"பதிக எண்": "4.027",
		"பாடல்": "மடக்கினார் புலியின்"
	},
	{
		"வரிசை எண்": "13",
		"தலப் பெயர்": "திருவதிகை வீரட்டானம்",
		"பதிக எண்": "4.028",
		"பாடல்": "முன்பெலாம் இளைய"
	},
	{
		"வரிசை எண்": "14",
		"தலப் பெயர்": "திருவதிகை வீரட்டானம்",
		"பதிக எண்": "4.104",
		"பாடல்": "மாசிலொள் வாள்போல்"
	},
	{
		"வரிசை எண்": "15",
		"தலப் பெயர்": "திருவதிகை வீரட்டானம்",
		"பதிக எண்": "5.053",
		"பாடல்": "கோணன் மாமதி"
	},
	{
		"வரிசை எண்": "16",
		"தலப் பெயர்": "திருவதிகை வீரட்டானம்",
		"பதிக எண்": "5.054",
		"பாடல்": "எட்டு நாண்மலர்"
	},
	{
		"வரிசை எண்": "17",
		"தலப் பெயர்": "திருவதிகை வீரட்டானம்",
		"பதிக எண்": "6.004",
		"பாடல்": "சந்திரனை மாகங்கைத்"
	},
	{
		"வரிசை எண்": "18",
		"தலப் பெயர்": "திருவதிகை வீரட்டானம்",
		"பதிக எண்": "6.005",
		"பாடல்": "எல்லாஞ் சிவனென்ன"
	},
	{
		"வரிசை எண்": "19",
		"தலப் பெயர்": "திருவதிகை வீரட்டானம்",
		"பதிக எண்": "6.006",
		"பாடல்": "அரவணையான் சிந்தித்"
	},
	{
		"வரிசை எண்": "20",
		"தலப் பெயர்": "திருவதிகை வீரட்டானம்",
		"பதிக எண்": "6.007",
		"பாடல்": "செல்வப் புனற்கெடில"
	},
	{
		"வரிசை எண்": "21",
		"தலப் பெயர்": "திருமுண்டீச்சுரம்",
		"பதிக எண்": "6.085",
		"பாடல்": "ஆர்த்தான் காண்"
	},
	{
		"வரிசை எண்": "22",
		"தலப் பெயர்": "திருவாமாத்தூர்",
		"பதிக எண்": "5.044",
		"பாடல்": "மாமாத் தாகிய"
	},
	{
		"வரிசை எண்": "23",
		"தலப் பெயர்": "திருவாமாத்தூர்",
		"பதிக எண்": "6.009",
		"பாடல்": "வண்ணங்கள் தாம்பாடி"
	},
	{
		"வரிசை எண்": "24",
		"தலப் பெயர்": "திருக்கோவலூர்",
		"பதிக எண்": "4.069",
		"பாடல்": "செத்தையேன் சிதம்ப"
	},
	{
		"வரிசை எண்": "25",
		"தலப் பெயர்": "திருத்தூங்கானைமாடம்",
		"பதிக எண்": "4.109",
		"பாடல்": "பொன்னார் திருவடிக்"
	},
	{
		"வரிசை எண்": "26",
		"தலப் பெயர்": "திருநெல்வாயில் அரத்துறை",
		"பதிக எண்": "5.003",
		"பாடல்": "கடவு ளைக்கட"
	},
	{
		"வரிசை எண்": "27",
		"தலப் பெயர்": "திருமுதுகுன்றம்",
		"பதிக எண்": "6.068",
		"பாடல்": "கருமணியைக் கனகத்தின்"
	},
	{ "வரிசை எண்": "28", "தலப் பெயர்": "கோயில்", "பதிக எண்": "4.081", "பாடல்": "கருநட்ட கண்டனை" },
	{ "வரிசை எண்": "29", "தலப் பெயர்": "கோயில்", "பதிக எண்": "4.023", "பாடல்": "பத்தனாய்ப் பாட" },
	{
		"வரிசை எண்": "30",
		"தலப் பெயர்": "கோயில்",
		"பதிக எண்": "5.001",
		"பாடல்": "அன்னம் பாலிக்குந்"
	},
	{
		"வரிசை எண்": "31",
		"தலப் பெயர்": "திருவேட்களம்",
		"பதிக எண்": "5.042",
		"பாடல்": "நன்று நாடொறும்"
	},
	{
		"வரிசை எண்": "32",
		"தலப் பெயர்": "திருக்கழிப்பாலை",
		"பதிக எண்": "4.006",
		"பாடல்": "வனபவள வாய்திறந்து"
	},
	{
		"வரிசை எண்": "33",
		"தலப் பெயர்": "திருக்கழிப்பாலை",
		"பதிக எண்": "4.030",
		"பாடல்": "நங்கையைப் பாகம்"
	},
	{
		"வரிசை எண்": "34",
		"தலப் பெயர்": "திருக்கழிப்பாலை",
		"பதிக எண்": "4.106",
		"பாடல்": "நெய்தற் குருகுதன்"
	},
	{
		"வரிசை எண்": "35",
		"தலப் பெயர்": "திருக்கழிப்பாலை",
		"பதிக எண்": "5.040",
		"பாடல்": "வண்ண மும்வடி"
	},
	{
		"வரிசை எண்": "36",
		"தலப் பெயர்": "திருக்கழிப்பாலை",
		"பதிக எண்": "6.012",
		"பாடல்": "ஊனுடுத்தி யொன்பது"
	},
	{ "வரிசை எண்": "37", "தலப் பெயர்": "கோயில்", "பதிக எண்": "5.002", "பாடல்": "பனைக்கை மும்மத" },
	{
		"வரிசை எண்": "38",
		"தலப் பெயர்": "கோயில்",
		"பதிக எண்": "6.001",
		"பாடல்": "அரியானை அந்தணர்தஞ்"
	},
	{ "வரிசை எண்": "39", "தலப் பெயர்": "கோயில்", "பதிக எண்": "4.022", "பாடல்": "செஞ்சடைக் கற்றை" },
	{ "வரிசை எண்": "40", "தலப் பெயர்": "கோயில்", "பதிக எண்": "4.080", "பாடல்": "பாளையு டைக்கமு" },
	{
		"வரிசை எண்": "41",
		"தலப் பெயர்": "கோயில்",
		"பதிக எண்": "6.002",
		"பாடல்": "மங்குல் மதிதவழும்"
	},
	{
		"வரிசை எண்": "42",
		"தலப் பெயர்": "திருநாரையூர்",
		"பதிக எண்": "5.055",
		"பாடல்": "வீறு தானுடை"
	},
	{
		"வரிசை எண்": "43",
		"தலப் பெயர்": "திருநாரையூர்",
		"பதிக எண்": "6.074",
		"பாடல்": "சொல்லானைப் பொருளானைச்"
	},
	{
		"வரிசை எண்": "44",
		"தலப் பெயர்": "ஸ்ரீ காழி",
		"பதிக எண்": "4.082",
		"பாடல்": "பார்கொண்டு மூடிக்"
	},
	{
		"வரிசை எண்": "45",
		"தலப் பெயர்": "ஸ்ரீ காழி",
		"பதிக எண்": "4.083",
		"பாடல்": "படையார் மழுவொன்று"
	},
	{ "வரிசை எண்": "46", "தலப் பெயர்": "ஸ்ரீ காழி", "பதிக எண்": "5.045", "பாடல்": "மாதி யன்று" },
	{
		"வரிசை எண்": "47",
		"தலப் பெயர்": "திருப்புன்கூரும் திருநீடூரும்",
		"பதிக எண்": "6.011",
		"பாடல்": "பிறவாதே தோன்றிய"
	},
	{
		"வரிசை எண்": "48",
		"தலப் பெயர்": "திருக்குறுக்கை வீரட்டம்",
		"பதிக எண்": "4.049",
		"பாடல்": "ஆதியிற் பிரம"
	},
	{
		"வரிசை எண்": "49",
		"தலப் பெயர்": "திருக்குறுக்கை வீரட்டம்",
		"பதிக எண்": "4.050",
		"பாடல்": "நெடியமால் பிரம"
	},
	{
		"வரிசை எண்": "50",
		"தலப் பெயர்": "திருநின்றியூர்",
		"பதிக எண்": "5.023",
		"பாடல்": "கொடுங்கண் வெண்டலை"
	},
	{
		"வரிசை எண்": "51",
		"தலப் பெயர்": "திருநனிப்பள்ளி",
		"பதிக எண்": "4.070",
		"பாடல்": "முற்றுணை யாயி"
	},
	{
		"வரிசை எண்": "52",
		"தலப் பெயர்": "திருச்செம்பொன்பள்ளி",
		"பதிக எண்": "4.029",
		"பாடல்": "ஊனினுள் ளுயிரை"
	},
	{
		"வரிசை எண்": "53",
		"தலப் பெயர்": "திருச்செம்பொன்பள்ளி",
		"பதிக எண்": "5.036",
		"பாடல்": "கானறாத கடிபொழில்"
	},
	{
		"வரிசை எண்": "54",
		"தலப் பெயர்": "திருமயிலாடுதுறை",
		"பதிக எண்": "5.039",
		"பாடல்": "கொள்ளுங் காதன்மை"
	},
	{
		"வரிசை எண்": "55",
		"தலப் பெயர்": "திருத்துருத்தி",
		"பதிக எண்": "4.042",
		"பாடல்": "பொருத்திய குரம்பை"
	},
	{
		"வரிசை எண்": "56",
		"தலப் பெயர்": "திருஅன்னியூர்",
		"பதிக எண்": "5.008",
		"பாடல்": "பாறலைத்த படுவெண்"
	},
	{
		"வரிசை எண்": "57",
		"தலப் பெயர்": "திருஆப்பாடி",
		"பதிக எண்": "4.048",
		"பாடல்": "கடலகமேழி னோடும்"
	},
	{
		"வரிசை எண்": "58",
		"தலப் பெயர்": "திருஓமாம்புலியூர்",
		"பதிக எண்": "6.088",
		"பாடல்": "ஆராரும் மூவிலை"
	},
	{
		"வரிசை எண்": "59",
		"தலப் பெயர்": "திருக்கஞ்சனூர்",
		"பதிக எண்": "6.090",
		"பாடல்": "மூவிலை வேற்சூல"
	},
	{
		"வரிசை எண்": "60",
		"தலப் பெயர்": "திருக்கடம்பூர்",
		"பதிக எண்": "5.019",
		"பாடல்": "தளருங் கோளர"
	},
	{
		"வரிசை எண்": "61",
		"தலப் பெயர்": "திருக்கடம்பூர்",
		"பதிக எண்": "5.020",
		"பாடல்": "ஒருவராயிரு மூவரு"
	},
	{
		"வரிசை எண்": "62",
		"தலப் பெயர்": "திருக்குரக்குக்கா",
		"பதிக எண்": "5.075",
		"பாடல்": "மரக்கொக் காமென"
	},
	{
		"வரிசை எண்": "63",
		"தலப் பெயர்": "திருக்கோழம்பம்",
		"பதிக எண்": "5.064",
		"பாடல்": "வேழம் பத்தைவர்"
	},
	{
		"வரிசை எண்": "64",
		"தலப் பெயர்": "திருச்சாய்க்காடு",
		"பதிக எண்": "4.065",
		"பாடல்": "தோடுலா மலர்கள்"
	},
	{
		"வரிசை எண்": "65",
		"தலப் பெயர்": "திருச்சாய்க்காடு",
		"பதிக எண்": "6.082",
		"பாடல்": "வானத் திளமதியும்"
	},
	{
		"வரிசை எண்": "66",
		"தலப் பெயர்": "திருத்தென்குரங்காடுதுறை",
		"பதிக எண்": "5.063",
		"பாடல்": "இரங்கா வன்மனத்"
	},
	{
		"வரிசை எண்": "67",
		"தலப் பெயர்": "திருப்புள்ளிருக்குவேளூர்",
		"பதிக எண்": "5.079",
		"பாடல்": "வெள்ளெ ருக்கர"
	},
	{
		"வரிசை எண்": "68",
		"தலப் பெயர்": "திருப்புள்ளிருக்குவேளூர்",
		"பதிக எண்": "6.054",
		"பாடல்": "ஆண்டானை அடியேனை"
	},
	{
		"வரிசை எண்": "69",
		"தலப் பெயர்": "திருமங்கலக்குடி",
		"பதிக எண்": "5.073",
		"பாடல்": "தங்கலப்பிய தக்கன்"
	},
	{
		"வரிசை எண்": "70",
		"தலப் பெயர்": "திருமணஞ்சேரி",
		"பதிக எண்": "5.087",
		"பாடல்": "பட்ட நெற்றியர்"
	},
	{
		"வரிசை எண்": "71",
		"தலப் பெயர்": "திருவெண்காடு",
		"பதிக எண்": "5.049",
		"பாடல்": "பண்காட் டிப்படி"
	},
	{
		"வரிசை எண்": "72",
		"தலப் பெயர்": "திருவெண்காடு",
		"பதிக எண்": "6.035",
		"பாடல்": "தூண்டு சுடர்மேனித்"
	},
	{
		"வரிசை எண்": "73",
		"தலப் பெயர்": "திருக்கோடிகா",
		"பதிக எண்": "4.051",
		"பாடல்": "நெற்றிமேற் கண்ணி"
	},
	{
		"வரிசை எண்": "74",
		"தலப் பெயர்": "திருக்கோடிகா",
		"பதிக எண்": "5.078",
		"பாடல்": "சங்கு லாமுன்கைத்"
	},
	{
		"வரிசை எண்": "75",
		"தலப் பெயர்": "திருக்கோடிகா",
		"பதிக எண்": "6.081",
		"பாடல்": "கண்டலஞ்சேர் நெற்றியிளங்"
	},
	{
		"வரிசை எண்": "76",
		"தலப் பெயர்": "திருவாவடுதுறை",
		"பதிக எண்": "6.046",
		"பாடல்": "நம்பனை நால்வேதங்"
	},
	{
		"வரிசை எண்": "77",
		"தலப் பெயர்": "திருவாவடுதுறை",
		"பதிக எண்": "5.029",
		"பாடல்": "நிறைக்க வாலியள்"
	},
	{
		"வரிசை எண்": "78",
		"தலப் பெயர்": "திருவாவடுதுறை",
		"பதிக எண்": "4.057",
		"பாடல்": "மஞ்சனே மணியு"
	},
	{
		"வரிசை எண்": "79",
		"தலப் பெயர்": "திருவாவடுதுறை",
		"பதிக எண்": "6.047",
		"பாடல்": "திருவேயென் செல்வமே"
	},
	{
		"வரிசை எண்": "80",
		"தலப் பெயர்": "திருவிடைமருதூர்",
		"பதிக எண்": "4.035",
		"பாடல்": "காடுடைச் சுடலை"
	},
	{
		"வரிசை எண்": "81",
		"தலப் பெயர்": "திருவிடைமருதூர்",
		"பதிக எண்": "5.014",
		"பாடல்": "பாச மொன்றில"
	},
	{
		"வரிசை எண்": "82",
		"தலப் பெயர்": "திருவிடைமருதூர்",
		"பதிக எண்": "5.015",
		"பாடல்": "பறையி னோசையும்"
	},
	{
		"வரிசை எண்": "83",
		"தலப் பெயர்": "திருவிடைமருதூர்",
		"பதிக எண்": "6.016",
		"பாடல்": "சூலப் படையுடையார்"
	},
	{
		"வரிசை எண்": "84",
		"தலப் பெயர்": "திருவிடைமருதூர்",
		"பதிக எண்": "6.017",
		"பாடல்": "ஆறு சடைக்கணிவர்"
	},
	{
		"வரிசை எண்": "85",
		"தலப் பெயர்": "திருநாகேச்சரம்",
		"பதிக எண்": "4.066",
		"பாடல்": "கச்சைசேர ரவர்"
	},
	{
		"வரிசை எண்": "86",
		"தலப் பெயர்": "திருநாகேச்சரம்",
		"பதிக எண்": "5.052",
		"பாடல்": "நல்லர் நல்லதோர்"
	},
	{
		"வரிசை எண்": "87",
		"தலப் பெயர்": "திருநாகேச்சரம்",
		"பதிக எண்": "6.066",
		"பாடல்": "தாயவனை வானோர்க்கும்"
	},
	{
		"வரிசை எண்": "88",
		"தலப் பெயர்": "திருச்சத்திமுற்றம்",
		"பதிக எண்": "4.096",
		"பாடல்": "கோவாய் முடுகி"
	},
	{
		"வரிசை எண்": "89",
		"தலப் பெயர்": "திருநல்லூர்",
		"பதிக எண்": "6.014",
		"பாடல்": "நினைந்துருகும் அடியாரை"
	},
	{
		"வரிசை எண்": "90",
		"தலப் பெயர்": "திருநல்லூர்",
		"பதிக எண்": "4.097",
		"பாடல்": "அட்டுமினில் பலி"
	},
	{
		"வரிசை எண்": "91",
		"தலப் பெயர்": "திருக்கருகாவூர்",
		"பதிக எண்": "6.015",
		"பாடல்": "குருகாம் வயிரமாங்"
	},
	{
		"வரிசை எண்": "92",
		"தலப் பெயர்": "திருப்பாலைத்துறை",
		"பதிக எண்": "5.051",
		"பாடல்": "நீல மாமணி"
	},
	{
		"வரிசை எண்": "93",
		"தலப் பெயர்": "பொது - விடந்தீர்த்தத் திருப்பதிகம்",
		"பதிக எண்": "4.018",
		"பாடல்": "ஒன்றுகொ லாமவர்"
	},
	{
		"வரிசை எண்": "94",
		"தலப் பெயர்": "திருப்பழனம்",
		"பதிக எண்": "4.012",
		"பாடல்": "சொன்மாலை பயில்கின்ற"
	},
	{
		"வரிசை எண்": "95",
		"தலப் பெயர்": "திருப்பழனம்",
		"பதிக எண்": "4.036",
		"பாடல்": "ஆடினா ரொருவர்"
	},
	{
		"வரிசை எண்": "96",
		"தலப் பெயர்": "திருப்பழனம்",
		"பதிக எண்": "4.087",
		"பாடல்": "மேவித்து நின்று"
	},
	{
		"வரிசை எண்": "97",
		"தலப் பெயர்": "திருப்பழனம்",
		"பதிக எண்": "5.035",
		"பாடல்": "அருவ னாய்அத்தி"
	},
	{
		"வரிசை எண்": "98",
		"தலப் பெயர்": "திருப்பழனம்",
		"பதிக எண்": "6.036",
		"பாடல்": "அலையார் கடல்நஞ்ச"
	},
	{
		"வரிசை எண்": "99",
		"தலப் பெயர்": "திருச்சோற்றுத்துறை",
		"பதிக எண்": "4.041",
		"பாடல்": "பொய்விரா மேனி"
	},
	{
		"வரிசை எண்": "100",
		"தலப் பெயர்": "திருச்சோற்றுத்துறை",
		"பதிக எண்": "4.085",
		"பாடல்": "காலை யெழுந்து"
	},
	{
		"வரிசை எண்": "101",
		"தலப் பெயர்": "திருச்சோற்றுத்துறை",
		"பதிக எண்": "5.033",
		"பாடல்": "கொல்லை யேற்றினர்"
	},
	{
		"வரிசை எண்": "102",
		"தலப் பெயர்": "திருச்சோற்றுத்துறை",
		"பதிக எண்": "6.044",
		"பாடல்": "மூத்தவனாய் உலகுக்கு"
	},
	{
		"வரிசை எண்": "103",
		"தலப் பெயர்": "திருக்கண்டியூர்",
		"பதிக எண்": "4.093",
		"பாடல்": "வானவர் தானவர்"
	},
	{
		"வரிசை எண்": "104",
		"தலப் பெயர்": "திருவேதிகுடி",
		"பதிக எண்": "4.090",
		"பாடல்": "கையது காலெரி"
	},
	{
		"வரிசை எண்": "105",
		"தலப் பெயர்": "திருவலஞ்சுழி",
		"பதிக எண்": "5.066",
		"பாடல்": "ஓதமார்கட லின்விட"
	},
	{
		"வரிசை எண்": "106",
		"தலப் பெயர்": "திருவலஞ்சுழி",
		"பதிக எண்": "6.072",
		"பாடல்": "அலையார் புனற்கங்கை"
	},
	{
		"வரிசை எண்": "107",
		"தலப் பெயர்": "திருவலஞ்சுழியும் திருக்கொட்டையூரும்",
		"பதிக எண்": "6.073",
		"பாடல்": "கருமணிபோற் கண்டத்"
	},
	{
		"வரிசை எண்": "108",
		"தலப் பெயர்": "திருக்குடமூக்கு",
		"பதிக எண்": "5.022",
		"பாடல்": "பூவணத்தவன் புண்ணியன்"
	},
	{
		"வரிசை எண்": "109",
		"தலப் பெயர்": "திருச்சேறை",
		"பதிக எண்": "4.073",
		"பாடல்": "பெருந்திரு இமவான்"
	},
	{
		"வரிசை எண்": "110",
		"தலப் பெயர்": "திருச்சேறை",
		"பதிக எண்": "5.077",
		"பாடல்": "பூரியாவரும் புண்ணியம்"
	},
	{
		"வரிசை எண்": "111",
		"தலப் பெயர்": "திருவாஞ்சியம்",
		"பதிக எண்": "5.067",
		"பாடல்": "படையும் பூதமும்"
	},
	{
		"வரிசை எண்": "112",
		"தலப் பெயர்": "திருப்பெருவேளூர்",
		"பதிக எண்": "4.060",
		"பாடல்": "மறையணி நாவி"
	},
	{
		"வரிசை எண்": "113",
		"தலப் பெயர்": "திருஆரூர்",
		"பதிக எண்": "4.101",
		"பாடல்": "குலம்பலம் பாவரு"
	},
	{
		"வரிசை எண்": "114",
		"தலப் பெயர்": "திருஆரூர்",
		"பதிக எண்": "4.020",
		"பாடல்": "காண்டலே கருத்"
	},
	{
		"வரிசை எண்": "115",
		"தலப் பெயர்": "திருஆரூர்",
		"பதிக எண்": "4.005",
		"பாடல்": "மெய்யெலாம் வெண்ணீறு"
	},
	{
		"வரிசை எண்": "116",
		"தலப் பெயர்": "திருஆரூர்",
		"பதிக எண்": "4.004",
		"பாடல்": "பாடிளம் பூதத்தி"
	},
	{
		"வரிசை எண்": "117",
		"தலப் பெயர்": "திருஆரூர்",
		"பதிக எண்": "4.019",
		"பாடல்": "சூலப் படையானைச்"
	},
	{
		"வரிசை எண்": "118",
		"தலப் பெயர்": "திருஆரூர்",
		"பதிக எண்": "4.052",
		"பாடல்": "படுகுழிப் பவ்வத்"
	},
	{
		"வரிசை எண்": "119",
		"தலப் பெயர்": "திருஆரூர்",
		"பதிக எண்": "4.053",
		"பாடல்": "குழல்வலங் கொண்ட"
	},
	{
		"வரிசை எண்": "120",
		"தலப் பெயர்": "திருஆரூர்",
		"பதிக எண்": "5.006",
		"பாடல்": "எப்போ தும்மிறை யும்மற"
	},
	{
		"வரிசை எண்": "121",
		"தலப் பெயர்": "திருஆரூர்",
		"பதிக எண்": "5.007",
		"பாடல்": "கொக்க ரைகுழல்"
	},
	{
		"வரிசை எண்": "122",
		"தலப் பெயர்": "திருஆரூர்",
		"பதிக எண்": "6.024",
		"பாடல்": "கைம்மான மதகளிற்றி"
	},
	{
		"5": "திருஆரூர்",
		"6": "6.026",
		"7": "பாதித்தன் திருவுருவிற்",
		"வரிசை எண்": "123",
		"தலப் பெயர்": "திருஆரூர்",
		"பதிக எண்": "6.025",
		"பாடல்": "124"
	},
	{
		"வரிசை எண்": "125",
		"தலப் பெயர்": "திருஆரூர்",
		"பதிக எண்": "6.028",
		"பாடல்": "நீற்றினையும் நெற்றிமே"
	},
	{
		"வரிசை எண்": "126",
		"தலப் பெயர்": "திருஆரூர்",
		"பதிக எண்": "6.029",
		"பாடல்": "திருமணியைத் தித்திக்குந்"
	},
	{
		"வரிசை எண்": "127",
		"தலப் பெயர்": "திருஆரூர்",
		"பதிக எண்": "6.030",
		"பாடல்": "எம்பந்த வல்வினை"
	},
	{
		"வரிசை எண்": "128",
		"தலப் பெயர்": "திருஆரூர்",
		"பதிக எண்": "6.031",
		"பாடல்": "இடர்கெடுமா றெண்ணு"
	},
	{
		"வரிசை எண்": "129",
		"தலப் பெயர்": "திருஆரூர்",
		"பதிக எண்": "6.032",
		"பாடல்": "கற்றவர்க ளுண்ணுங்"
	},
	{
		"வரிசை எண்": "130",
		"தலப் பெயர்": "திருஆரூர்",
		"பதிக எண்": "6.034",
		"பாடல்": "ஒருவனாய் உலகேத்த"
	},
	{
		"வரிசை எண்": "131",
		"தலப் பெயர்": "திருஆரூர்",
		"பதிக எண்": "4.102",
		"பாடல்": "வேம்பினைப் பேசி"
	},
	{
		"வரிசை எண்": "132",
		"தலப் பெயர்": "திருஆரூர் அரநெறி",
		"பதிக எண்": "4.017",
		"பாடல்": "எத்தீ புகினும்"
	},
	{
		"வரிசை எண்": "133",
		"தலப் பெயர்": "திருஆரூர் அரநெறி",
		"பதிக எண்": "6.033",
		"பாடல்": "பொருங்கைமதக் கரியுரி"
	},
	{
		"வரிசை எண்": "134",
		"தலப் பெயர்": "திருவலிவலம்",
		"பதிக எண்": "6.048",
		"பாடல்": "நல்லான்காண் நான்மறை"
	},
	{
		"வரிசை எண்": "135",
		"தலப் பெயர்": "திருக்கீழ்வேளூர்",
		"பதிக எண்": "6.067",
		"பாடல்": "ஆளான அடியவர்கட்"
	},
	{
		"வரிசை எண்": "136",
		"தலப் பெயர்": "திருக்கன்றாப்பூர்",
		"பதிக எண்": "6.061",
		"பாடல்": "மாதினையோர் கூறுகந்தாய்"
	},
	{
		"வரிசை எண்": "137",
		"தலப் பெயர்": "திருப்பயற்றூர்",
		"பதிக எண்": "4.032",
		"பாடல்": "உரித்திட்டார் ஆனை"
	},
	{
		"வரிசை எண்": "138",
		"தலப் பெயர்": "திருப்பள்ளியின் முக்கூடல்",
		"பதிக எண்": "6.069",
		"பாடல்": "ஆராத இன்னமுதை"
	},
	{ "வரிசை எண்": "139", "தலப் பெயர்": "திருஆரூர்", "பதிக எண்": "4.021", "பாடல்": "முத்து விதான" },
	{
		"வரிசை எண்": "140",
		"தலப் பெயர்": "திருப்புகலூர்",
		"பதிக எண்": "5.046",
		"பாடல்": "துன்னக் கோவணச்"
	},
	{
		"வரிசை எண்": "141",
		"தலப் பெயர்": "திருச்செங்காட்டங்குடி",
		"பதிக எண்": "6.084",
		"பாடல்": "பெருந்தகையைப் பெறற்கரிய"
	},
	{
		"வரிசை எண்": "142",
		"தலப் பெயர்": "திருநள்ளாறு",
		"பதிக எண்": "5.068",
		"பாடல்": "உள்ளா றாததோர்"
	},
	{
		"வரிசை எண்": "143",
		"தலப் பெயர்": "திருநள்ளாறு",
		"பதிக எண்": "6.020",
		"பாடல்": "ஆதிக்கண் ணான்முகத்தி"
	},
	{
		"வரிசை எண்": "144",
		"தலப் பெயர்": "திருமருகல்",
		"பதிக எண்": "5.088",
		"பாடல்": "பெருக லாந்தவம்"
	},
	{
		"வரிசை எண்": "145",
		"தலப் பெயர்": "திருக்கடவூர் வீரட்டம்",
		"பதிக எண்": "4.031",
		"பாடல்": "பொள்ளத்த காய"
	},
	{
		"வரிசை எண்": "146",
		"தலப் பெயர்": "திருக்கடவூர் வீரட்டம்",
		"பதிக எண்": "4.107",
		"பாடல்": "மருட்டுயர் தீரவன்"
	},
	{
		"வரிசை எண்": "147",
		"தலப் பெயர்": "திருக்கடவூர் வீரட்டம்",
		"பதிக எண்": "5.037",
		"பாடல்": "மலைக்கொ ளானை"
	},
	{
		"வரிசை எண்": "148",
		"தலப் பெயர்": "திருக்கடவூர் மயானம்",
		"பதிக எண்": "5.038",
		"பாடல்": "குழைகொள் காதினர்"
	},
	{
		"வரிசை எண்": "149",
		"தலப் பெயர்": "திருஆக்கூர்",
		"பதிக எண்": "6.021",
		"பாடல்": "முடித்தா மரையணிந்த"
	},
	{
		"வரிசை எண்": "150",
		"தலப் பெயர்": "திருமீயச்சூர் இளங்கோயில்",
		"பதிக எண்": "5.011",
		"பாடல்": "தோற்றுங் கோயிலுந்"
	},
	{
		"வரிசை எண்": "151",
		"தலப் பெயர்": "திருவலம்புரம்",
		"பதிக எண்": "4.055",
		"பாடல்": "தெண்டிரை தேங்கி"
	},
	{
		"வரிசை எண்": "152",
		"தலப் பெயர்": "திருவலம்புரம்",
		"பதிக எண்": "6.058",
		"பாடல்": "மண்ணளந்த மணிவண்ணர்"
	},
	{
		"வரிசை எண்": "153",
		"தலப் பெயர்": "திருவீழிமிழலை",
		"பதிக எண்": "6.050",
		"பாடல்": "போரானை ஈருரிவைப்"
	},
	{
		"வரிசை எண்": "154",
		"தலப் பெயர்": "திருவீழிமிழலை",
		"பதிக எண்": "4.064",
		"பாடல்": "பூதத்தின் படையர்"
	},
	{
		"வரிசை எண்": "155",
		"தலப் பெயர்": "திருவீழிமிழலை",
		"பதிக எண்": "4.095",
		"பாடல்": "வான்சொட்டச் சொட்டநின்"
	},
	{
		"வரிசை எண்": "156",
		"தலப் பெயர்": "திருவீழிமிழலை",
		"பதிக எண்": "5.012",
		"பாடல்": "கரைந்து கைதொழு"
	},
	{
		"வரிசை எண்": "157",
		"தலப் பெயர்": "திருவீழிமிழலை",
		"பதிக எண்": "5.013",
		"பாடல்": "என்பொ னேயிமை"
	},
	{
		"வரிசை எண்": "158",
		"தலப் பெயர்": "திருவீழிமிழலை",
		"பதிக எண்": "6.051",
		"பாடல்": "கயிலாய மலையுள்ளார்"
	},
	{
		"வரிசை எண்": "159",
		"தலப் பெயர்": "திருவீழிமிழலை",
		"பதிக எண்": "6.052",
		"பாடல்": "கண்ணவன் காண்"
	},
	{
		"வரிசை எண்": "160",
		"தலப் பெயர்": "திருவீழிமிழலை",
		"பதிக எண்": "6.053",
		"பாடல்": "மானேறு கரமுடைய"
	},
	{
		"வரிசை எண்": "161",
		"தலப் பெயர்": "திருக்கொண்டீச்சரம்",
		"பதிக எண்": "4.067",
		"பாடல்": "வரைகிலேன் புலன்க"
	},
	{
		"வரிசை எண்": "162",
		"தலப் பெயர்": "திருக்கொண்டீச்சரம்",
		"பதிக எண்": "5.070",
		"பாடல்": "கண்ட பேச்சினிற்"
	},
	{
		"வரிசை எண்": "163",
		"தலப் பெயர்": "திருக்கோளிலி",
		"பதிக எண்": "5.056",
		"பாடல்": "மைக்கொள் கண்ணுமை"
	},
	{
		"வரிசை எண்": "164",
		"தலப் பெயர்": "திருக்கோளிலி",
		"பதிக எண்": "5.057",
		"பாடல்": "முன்ன மேநினை"
	},
	{
		"வரிசை எண்": "165",
		"தலப் பெயர்": "திருத்தலையாலங்காடு",
		"பதிக எண்": "6.079",
		"பாடல்": "தொண்டர்க்குத் தூநெறியாய்"
	},
	{
		"வரிசை எண்": "166",
		"தலப் பெயர்": "திருப்பேரெயில்",
		"பதிக எண்": "5.016",
		"பாடல்": "மறையு மோதுவர்"
	},
	{
		"வரிசை எண்": "167",
		"தலப் பெயர்": "திருமறைக்காடு",
		"பதிக எண்": "5.010",
		"பாடல்": "பண்ணி னேர்மொழி"
	},
	{
		"வரிசை எண்": "168",
		"தலப் பெயர்": "திருமறைக்காடு",
		"பதிக எண்": "4.033",
		"பாடல்": "இந்திரனோடு தேவர்"
	},
	{
		"வரிசை எண்": "169",
		"தலப் பெயர்": "திருமறைக்காடு",
		"பதிக எண்": "4.034",
		"பாடல்": "தேரையு மேல்க"
	},
	{
		"வரிசை எண்": "170",
		"தலப் பெயர்": "திருமறைக்காடு",
		"பதிக எண்": "5.009",
		"பாடல்": "ஓதமால்கடல் பாவி"
	},
	{
		"வரிசை எண்": "171",
		"தலப் பெயர்": "திருமறைக்காடு",
		"பதிக எண்": "6.023",
		"பாடல்": "தூண்டு சுடரனைய"
	},
	{
		"வரிசை எண்": "172",
		"தலப் பெயர்": "திருவாய்மூர்",
		"பதிக எண்": "5.050",
		"பாடல்": "எங்கேயென் னையிருந்து"
	},
	{
		"வரிசை எண்": "173",
		"தலப் பெயர்": "திருவாய்மூர்",
		"பதிக எண்": "6.077",
		"பாடல்": "பாடவடியார் பரவக்"
	},
	{
		"வரிசை எண்": "174",
		"தலப் பெயர்": "திருநாகைக்காரோணம்",
		"பதிக எண்": "4.071",
		"பாடல்": "மனைவிதாய் தந்தை"
	},
	{
		"வரிசை எண்": "175",
		"தலப் பெயர்": "திருநாகைக்காரோணம்",
		"பதிக எண்": "4.103",
		"பாடல்": "வடிவுடை மாமலை"
	},
	{
		"வரிசை எண்": "176",
		"தலப் பெயர்": "திருநாகைக்காரோணம்",
		"பதிக எண்": "5.083",
		"பாடல்": "பாணத் தான்மதில்"
	},
	{
		"வரிசை எண்": "177",
		"தலப் பெயர்": "திருநாகைக்காரோணம்",
		"பதிக எண்": "6.022",
		"பாடல்": "பாரார்பரவும் பழனத்"
	},
	{
		"வரிசை எண்": "178",
		"தலப் பெயர்": "திருவாவடுதுறை",
		"பதிக எண்": "4.056",
		"பாடல்": "மாயிருஞால மெல்லாம்"
	},
	{
		"வரிசை எண்": "179",
		"தலப் பெயர்": "திருப்பழையாறை வடதளி",
		"பதிக எண்": "5.058",
		"பாடல்": "தலையெ லாம்பறிக்"
	},
	{
		"வரிசை எண்": "180",
		"தலப் பெயர்": "திருஅரிசிற்கரைப்புத்தூர்",
		"பதிக எண்": "5.061",
		"பாடல்": "முத்தூ ரும்புனல்"
	},
	{
		"வரிசை எண்": "181",
		"தலப் பெயர்": "திருஅவளிவணல்லூர்",
		"பதிக எண்": "4.059",
		"பாடல்": "தோற்றினான் எயிறு"
	},
	{
		"வரிசை எண்": "182",
		"தலப் பெயர்": "திருஅன்பிலாலந்துறை",
		"பதிக எண்": "5.080",
		"பாடல்": "வானஞ்சேர் மதிசூடிய"
	},
	{
		"வரிசை எண்": "183",
		"தலப் பெயர்": "திருஆலம்பொழில்",
		"பதிக எண்": "6.086",
		"பாடல்": "கருவாகிக் கண்ணுதலாய்"
	},
	{
		"வரிசை எண்": "184",
		"தலப் பெயர்": "திருஇன்னம்பர்",
		"பதிக எண்": "4.072",
		"பாடல்": "விண்ணவர் மகுட"
	},
	{
		"வரிசை எண்": "185",
		"தலப் பெயர்": "திருஇன்னம்பர்",
		"பதிக எண்": "4.100",
		"பாடல்": "மன்னு மலைமகள்"
	},
	{
		"வரிசை எண்": "186",
		"தலப் பெயர்": "திருஇன்னம்பர்",
		"பதிக எண்": "5.021",
		"பாடல்": "என்னிலாரும் எனக்கினி"
	},
	{
		"வரிசை எண்": "187",
		"தலப் பெயர்": "திருஇன்னம்பர்",
		"பதிக எண்": "6.089",
		"பாடல்": "அல்லி மலர்நாற்றத்"
	},
	{
		"வரிசை எண்": "188",
		"தலப் பெயர்": "திருக்கடம்பந்துறை",
		"பதிக எண்": "5.018",
		"பாடல்": "முற்றி லாமுலை"
	},
	{
		"வரிசை எண்": "189",
		"தலப் பெயர்": "திருக்கடுவாய்க்கரைப்புத்தூர்",
		"பதிக எண்": "5.062",
		"பாடல்": "ஒருத்தனை மூவுலகொடு"
	},
	{
		"வரிசை எண்": "190",
		"தலப் பெயர்": "திருக்கருவிலிக்கொட்டிட்டை",
		"பதிக எண்": "5.069",
		"பாடல்": "மட்டிட்டகுழ லார்சுழ"
	},
	{
		"வரிசை எண்": "191",
		"தலப் பெயர்": "திருக்காட்டுப்பள்ளி (மேலை)",
		"பதிக எண்": "5.084",
		"பாடல்": "மாட்டுப் பள்ளி"
	},
	{
		"வரிசை எண்": "192",
		"தலப் பெயர்": "திருக்கானூர்",
		"பதிக எண்": "5.076",
		"பாடல்": "திருவின் நாதனுஞ்"
	},
	{
		"வரிசை எண்": "193",
		"தலப் பெயர்": "திருக்குடந்தைக்கீழ்க்கோட்டம்",
		"பதிக எண்": "6.075",
		"பாடல்": "சொன்மலிந்த மறைநான்கா"
	},
	{
		"வரிசை எண்": "194",
		"தலப் பெயர்": "திருச்சிவபுரம்",
		"பதிக எண்": "6.087",
		"பாடல்": "வானவன்காண் வானவர்க்கும்"
	},
	{
		"வரிசை எண்": "195",
		"தலப் பெயர்": "திருநல்லம்",
		"பதிக எண்": "5.043",
		"பாடல்": "கொல்லத் தான்நம"
	},
	{
		"வரிசை எண்": "196",
		"தலப் பெயர்": "திருநீலக்குடி",
		"பதிக எண்": "5.072",
		"பாடல்": "வைத்தமாடும் மனைவியும்"
	},
	{
		"வரிசை எண்": "197",
		"தலப் பெயர்": "திருப்பந்தணைநல்லூர்",
		"பதிக எண்": "6.010",
		"பாடல்": "நோதங்க மில்லாதார்"
	},
	{
		"வரிசை எண்": "198",
		"தலப் பெயர்": "திருப்பாண்டிக்கொடுமுடி",
		"பதிக எண்": "5.081",
		"பாடல்": "சிட்டனைச்சிவ னைச்"
	},
	{
		"வரிசை எண்": "199",
		"தலப் பெயர்": "திருப்புறம்பயம்",
		"பதிக எண்": "6.013",
		"பாடல்": "கொடிமாட நீடெருவு"
	},
	{
		"வரிசை எண்": "200",
		"தலப் பெயர்": "திருப்பூவனூர்",
		"பதிக எண்": "5.065",
		"பாடல்": "பூவனூர்ப்புனி தன்றிரு"
	},
	{
		"வரிசை எண்": "201",
		"தலப் பெயர்": "திருவன்னியூர்",
		"பதிக எண்": "5.026",
		"பாடல்": "காடு கொண்டரங்"
	},
	{
		"வரிசை எண்": "202",
		"தலப் பெயர்": "திருவாட்போக்கி",
		"பதிக எண்": "5.086",
		"பாடல்": "காலபாசம் பிடித்தெழு"
	},
	{
		"வரிசை எண்": "203",
		"தலப் பெயர்": "திருவிசயமங்கை",
		"பதிக எண்": "5.071",
		"பாடல்": "குசையும் அங்கையிற்"
	},
	{
		"வரிசை எண்": "204",
		"தலப் பெயர்": "திருவெண்ணியூர்",
		"பதிக எண்": "5.017",
		"பாடல்": "முத்தி னைப்பவ"
	},
	{
		"வரிசை எண்": "205",
		"தலப் பெயர்": "திருவெண்ணியூர்",
		"பதிக எண்": "6.059",
		"பாடல்": "தொண்டிலங்கும் அடியவ"
	},
	{
		"வரிசை எண்": "206",
		"தலப் பெயர்": "திருஆனைக்கா",
		"பதிக எண்": "5.031",
		"பாடல்": "கோனைக் காவிக்"
	},
	{
		"வரிசை எண்": "207",
		"தலப் பெயர்": "திருஆனைக்கா",
		"பதிக எண்": "6.062",
		"பாடல்": "எத்தாயர் எத்தந்தை"
	},
	{
		"வரிசை எண்": "208",
		"தலப் பெயர்": "திருஆனைக்கா",
		"பதிக எண்": "6.063",
		"பாடல்": "முன்னானைத் தோல்போர்த்த"
	},
	{
		"வரிசை எண்": "209",
		"தலப் பெயர்": "திருஎறும்பியூர்",
		"பதிக எண்": "5.074",
		"பாடல்": "விரும்பி யூறுவிடேல்"
	},
	{
		"வரிசை எண்": "210",
		"தலப் பெயர்": "திருஎறும்பியூர்",
		"பதிக எண்": "6.091",
		"பாடல்": "பன்னியசெந் தமிழறியேன்"
	},
	{
		"வரிசை எண்": "211",
		"தலப் பெயர்": "திரிச்சிராப்பள்ளி",
		"பதிக எண்": "5.085",
		"பாடல்": "மட்டுவார்குழ லாளொடு"
	},
	{
		"வரிசை எண்": "212",
		"தலப் பெயர்": "திருக்கற்குடி",
		"பதிக எண்": "6.060",
		"பாடல்": "மூத்தவனை வானவர்க்கு"
	},
	{
		"வரிசை எண்": "213",
		"தலப் பெயர்": "திருப்பராய்த்துறை",
		"பதிக எண்": "5.030",
		"பாடல்": "கரப்பர்கால மடைந்தவர்"
	},
	{
		"வரிசை எண்": "214",
		"தலப் பெயர்": "திருப்பைஞ்ஞீலி",
		"பதிக எண்": "5.041",
		"பாடல்": "உடையர் கோவண"
	},
	{
		"வரிசை எண்": "215",
		"தலப் பெயர்": "திருஅண்ணாமலை",
		"பதிக எண்": "4.063",
		"பாடல்": "ஓதிமா மலர்கள்"
	},
	{
		"வரிசை எண்": "216",
		"தலப் பெயர்": "திருஅண்ணாமலை",
		"பதிக எண்": "5.004",
		"பாடல்": "வட்டனைமதி சூடியை"
	},
	{
		"வரிசை எண்": "217",
		"தலப் பெயர்": "திருஅண்ணாமலை",
		"பதிக எண்": "5.005",
		"பாடல்": "பட்டிஏறுகந் தேறிப்"
	},
	{
		"வரிசை எண்": "218",
		"தலப் பெயர்": "திருகச்சியேகம்பம்",
		"பதிக எண்": "4.007",
		"பாடல்": "கரவாடும் வன்னெஞ்சர்க்"
	},
	{
		"வரிசை எண்": "219",
		"தலப் பெயர்": "திருகச்சியேகம்பம்",
		"பதிக எண்": "4.044",
		"பாடல்": "நம்பனை நகர"
	},
	{
		"வரிசை எண்": "220",
		"தலப் பெயர்": "திருகச்சியேகம்பம்",
		"பதிக எண்": "4.099",
		"பாடல்": "ஓதுவித் தாய்முன்"
	},
	{
		"வரிசை எண்": "221",
		"தலப் பெயர்": "திருகச்சியேகம்பம்",
		"பதிக எண்": "5.047",
		"பாடல்": "பண்டுசெய்த பழவினை"
	},
	{
		"வரிசை எண்": "222",
		"தலப் பெயர்": "திருகச்சியேகம்பம்",
		"பதிக எண்": "5.048",
		"பாடல்": "பூமேலானும் பூமகள்"
	},
	{
		"வரிசை எண்": "223",
		"தலப் பெயர்": "திருக்கச்சிமேற்றளி",
		"பதிக எண்": "4.043",
		"பாடல்": "மறையது பாடிப்"
	},
	{
		"வரிசை எண்": "224",
		"தலப் பெயர்": "திருமாற்பேறு",
		"பதிக எண்": "4.108",
		"பாடல்": "மாணிக் குயிர்பெறக்"
	},
	{
		"வரிசை எண்": "225",
		"தலப் பெயர்": "திருமாற்பேறு",
		"பதிக எண்": "5.059",
		"பாடல்": "பொருமாற் றின்படை"
	},
	{
		"வரிசை எண்": "226",
		"தலப் பெயர்": "திருமாற்பேறு",
		"பதிக எண்": "5.060",
		"பாடல்": "ஏதுமொன்று மறிவில"
	},
	{
		"வரிசை எண்": "227",
		"தலப் பெயர்": "திருமாற்பேறு",
		"பதிக எண்": "6.080",
		"பாடல்": "பாரானைப் பாரினது"
	},
	{
		"வரிசை எண்": "228",
		"தலப் பெயர்": "திருக்கச்சியேகம்பம்",
		"பதிக எண்": "6.064",
		"பாடல்": "கூற்றுவன் காண்கூற்"
	},
	{
		"வரிசை எண்": "229",
		"தலப் பெயர்": "திருக்கச்சியேகம்பம்",
		"பதிக எண்": "6.065",
		"பாடல்": "உரித்தவன் காண்உரக்"
	},
	{
		"வரிசை எண்": "230",
		"தலப் பெயர்": "திருக்கழுக்குன்றம்",
		"பதிக எண்": "6.092",
		"பாடல்": "மூவிலைவேற் கையானை"
	},
	{
		"வரிசை எண்": "231",
		"தலப் பெயர்": "திருவான்மியூர்",
		"பதிக எண்": "5.082",
		"பாடல்": "விண்ட மாமலர்"
	},
	{
		"வரிசை எண்": "232",
		"தலப் பெயர்": "திருவொற்றியூர்",
		"பதிக எண்": "6.045",
		"பாடல்": "வண்டோங்கு செங்கமலங்"
	},
	{
		"வரிசை எண்": "233",
		"தலப் பெயர்": "திருவொற்றியூர்",
		"பதிக எண்": "4.086",
		"பாடல்": "செற்றுக் களிற்றுரி"
	},
	{
		"வரிசை எண்": "234",
		"தலப் பெயர்": "திருவொற்றியூர்",
		"பதிக எண்": "5.024",
		"பாடல்": "ஒற்றியூரும் ஒளிமதி"
	},
	{
		"வரிசை எண்": "235",
		"தலப் பெயர்": "திருவொற்றியூர்",
		"பதிக எண்": "4.045",
		"பாடல்": "வெள்ளத்தைச் சடையில்"
	},
	{
		"வரிசை எண்": "236",
		"தலப் பெயர்": "திருவொற்றியூர்",
		"பதிக எண்": "4.046",
		"பாடல்": "ஓம்பினேன் கூட்டை"
	},
	{
		"வரிசை எண்": "237",
		"தலப் பெயர்": "திருப்பாசூர்",
		"பதிக எண்": "5.025",
		"பாடல்": "முந்திமூவெயி லெய்த"
	},
	{
		"வரிசை எண்": "238",
		"தலப் பெயர்": "திருப்பாசூர்",
		"பதிக எண்": "6.083",
		"பாடல்": "விண்ணாகி நிலனாகி"
	},
	{
		"வரிசை எண்": "239",
		"தலப் பெயர்": "திருஆலங்காடு",
		"பதிக எண்": "6.078",
		"பாடல்": "ஒன்றா வுலகனைத்து"
	},
	{
		"வரிசை எண்": "240",
		"தலப் பெயர்": "திருஆலங்காடு",
		"பதிக எண்": "4.068",
		"பாடல்": "வெள்ளநீர்ச் சடையர்"
	},
	{
		"வரிசை எண்": "241",
		"தலப் பெயர்": "திருக்காளத்தி",
		"பதிக எண்": "6.008",
		"பாடல்": "விற்றூணொன் றில்லாத"
	},
	{
		"வரிசை எண்": "242",
		"தலப் பெயர்": "திருப்பருப்பதம்",
		"பதிக எண்": "4.058",
		"பாடல்": "கன்றினார் புரங்கள்"
	},
	{
		"வரிசை எண்": "243",
		"தலப் பெயர்": "திருக்கோகரணம்",
		"பதிக எண்": "6.049",
		"பாடல்": "சந்திரனுந் தண்புனலுஞ்"
	},
	{
		"வரிசை எண்": "244",
		"தலப் பெயர்": "திருக்கயிலாயம்",
		"பதிக எண்": "6.055",
		"பாடல்": "வேற்றாகி விண்ணாகி"
	},
	{
		"வரிசை எண்": "245",
		"தலப் பெயர்": "திருக்கயிலாயம்",
		"பதிக எண்": "4.047",
		"பாடல்": "கனகமா வயிர"
	},
	{
		"வரிசை எண்": "246",
		"தலப் பெயர்": "திருக்கயிலாயம்",
		"பதிக எண்": "6.056",
		"பாடல்": "பொறையுடைய பூமிநீ"
	},
	{
		"வரிசை எண்": "247",
		"தலப் பெயர்": "திருக்கயிலாயம்",
		"பதிக எண்": "6.057",
		"பாடல்": "பாட்டான நல்ல"
	},
	{
		"வரிசை எண்": "248",
		"தலப் பெயர்": "திருஐயாறு",
		"பதிக எண்": "6.037",
		"பாடல்": "ஆரார் திரிபுரங்கள்"
	},
	{
		"வரிசை எண்": "249",
		"தலப் பெயர்": "திருஐயாறு",
		"பதிக எண்": "4.003",
		"பாடல்": "மாதர்ப் பிறைக்கண்ணி"
	},
	{ "வரிசை எண்": "250", "தலப் பெயர்": "திருஐயாறு", "பதிக எண்": "6.038", "பாடல்": "ஓசை ஒலியெலா" },
	{
		"வரிசை எண்": "251",
		"தலப் பெயர்": "திருஐயாறு",
		"பதிக எண்": "5.027",
		"பாடல்": "சிந்தை வாய்தலு"
	},
	{
		"வரிசை எண்": "252",
		"தலப் பெயர்": "திருஐயாறு",
		"பதிக எண்": "5.028",
		"பாடல்": "சிந்தை வண்ணத்த"
	},
	{
		"வரிசை எண்": "253",
		"தலப் பெயர்": "திருஐயாறு",
		"பதிக எண்": "4.038",
		"பாடல்": "கங்கையைச் சடையுள்"
	},
	{
		"வரிசை எண்": "254",
		"தலப் பெயர்": "திருஐயாறு",
		"பதிக எண்": "4.039",
		"பாடல்": "குண்டனாய்ச் சமண"
	},
	{ "வரிசை எண்": "255", "தலப் பெயர்": "திருஐயாறு", "பதிக எண்": "4.040", "பாடல்": "தானலா துலக" },
	{
		"வரிசை எண்": "256",
		"தலப் பெயர்": "திருஐயாறு",
		"பதிக எண்": "4.091",
		"பாடல்": "குறுவித்த வாகுற்ற"
	},
	{
		"வரிசை எண்": "257",
		"தலப் பெயர்": "திருஐயாறு",
		"பதிக எண்": "4.092",
		"பாடல்": "சிந்திப் பரியன"
	},
	{
		"வரிசை எண்": "258",
		"தலப் பெயர்": "திருஐயாறு",
		"பதிக எண்": "4.098",
		"பாடல்": "அந்திவட் டத்திங்கட்"
	},
	{
		"வரிசை எண்": "259",
		"தலப் பெயர்": "திருஐயாறு",
		"பதிக எண்": "4.013",
		"பாடல்": "விடகிலேன் அடிநாயேன்"
	},
	{
		"வரிசை எண்": "260",
		"தலப் பெயர்": "திருநெய்த்தானம்",
		"பதிக எண்": "4.037",
		"பாடல்": "காலனை வீழச்செற்ற"
	},
	{
		"வரிசை எண்": "261",
		"தலப் பெயர்": "திருநெய்த்தானம்",
		"பதிக எண்": "4.089",
		"பாடல்": "பாரிடஞ் சாடிய"
	},
	{
		"வரிசை எண்": "262",
		"தலப் பெயர்": "திருநெய்த்தானம்",
		"பதிக எண்": "5.034",
		"பாடல்": "கொல்லி யான்குளிர்"
	},
	{
		"வரிசை எண்": "263",
		"தலப் பெயர்": "திருநெய்த்தானம்",
		"பதிக எண்": "6.041",
		"பாடல்": "வகையெலா முடையாயும்"
	},
	{
		"வரிசை எண்": "264",
		"தலப் பெயர்": "திருநெய்த்தானம்",
		"பதிக எண்": "6.042",
		"பாடல்": "மெய்த்தானத் தகம்படியுள்"
	},
	{
		"வரிசை எண்": "265",
		"தலப் பெயர்": "திருமழபாடி",
		"பதிக எண்": "6.039",
		"பாடல்": "நீறேறு திருமேனி"
	},
	{
		"வரிசை எண்": "266",
		"தலப் பெயர்": "திருமழபாடி",
		"பதிக எண்": "6.040",
		"பாடல்": "அலையடுத்த பெருங்கட"
	},
	{
		"வரிசை எண்": "267",
		"தலப் பெயர்": "திருப்பூந்துருத்தி",
		"பதிக எண்": "6.043",
		"பாடல்": "நில்லாத நீர்சடை"
	},
	{
		"வரிசை எண்": "268",
		"தலப் பெயர்": "திருப்பூந்துருத்தி",
		"பதிக எண்": "5.032",
		"பாடல்": "கொடிகொள் செல்வ"
	},
	{
		"வரிசை எண்": "269",
		"தலப் பெயர்": "திருப்பூந்துருத்தி",
		"பதிக எண்": "4.088",
		"பாடல்": "மாலினை மாலுற"
	},
	{
		"வரிசை எண்": "270",
		"தலப் பெயர்": "பலவகைத் திருத்தாண்டகம்",
		"பதிக எண்": "6.093",
		"பாடல்": "நேர்ந்தொருத்தி ஒருபாகத்"
	},
	{
		"வரிசை எண்": "271",
		"தலப் பெயர்": "தனித் திருத்தாண்டகம்",
		"பதிக எண்": "6.096",
		"பாடல்": "ஆமயந்தீர்த் தடியேனை"
	},
	{
		"வரிசை எண்": "272",
		"தலப் பெயர்": "அடைவுத் திருத்தாண்டகம்",
		"பதிக எண்": "6.071",
		"பாடல்": "பொருப்பள்ளி வரைவில்லாப்"
	},
	{
		"வரிசை எண்": "273",
		"தலப் பெயர்": "திருஅங்கமாலை",
		"பதிக எண்": "4.009",
		"பாடல்": "தலையே நீவணங்காய்"
	},
	{
		"வரிசை எண்": "274",
		"தலப் பெயர்": "தனித் திருக்குறுந்தொகை",
		"பதிக எண்": "5.089",
		"பாடல்": "ஒன்று வெண்பிறைக்"
	},
	{
		"வரிசை எண்": "275",
		"தலப் பெயர்": "தனித் திருக்குறுந்தொகை",
		"பதிக எண்": "5.091",
		"பாடல்": "ஏயி லானையெ"
	},
	{
		"வரிசை எண்": "276",
		"தலப் பெயர்": "காலபாசத் திருக்குறுந்தொகை",
		"பதிக எண்": "5.092",
		"பாடல்": "கண்டு கொள்ளரி"
	},
	{
		"வரிசை எண்": "277",
		"தலப் பெயர்": "மறக்கிற்பனே திருக்குறுந்தொகை",
		"பதிக எண்": "5.093",
		"பாடல்": "காச னைக்கன"
	},
	{
		"வரிசை எண்": "278",
		"தலப் பெயர்": "தொழற்பாலதே திருக்குறுந்தொகை",
		"பதிக எண்": "5.094",
		"பாடல்": "அண்டத் தானை"
	},
	{
		"வரிசை எண்": "279",
		"தலப் பெயர்": "இலிங்கபுராணம் திருக்குறுந்தொகை",
		"பதிக எண்": "5.095",
		"பாடல்": "புக்கணைந்து புரிந்தல"
	},
	{
		"வரிசை எண்": "280",
		"தலப் பெயர்": "மனத்தொகை திருக்குறுந்தொகை",
		"பதிக எண்": "5.096",
		"பாடல்": "பொன்னுள் ளத்திரள்"
	},
	{
		"வரிசை எண்": "281",
		"தலப் பெயர்": "சித்தத்தொகை திருக்குறுந்தொகை",
		"பதிக எண்": "5.097",
		"பாடல்": "சிந்திப் பார்மனத்"
	},
	{
		"வரிசை எண்": "282",
		"தலப் பெயர்": "உள்ளத் திருக்குறுந்தொகை",
		"பதிக எண்": "5.098",
		"பாடல்": "நீற லைத்ததோர்"
	},
	{
		"வரிசை எண்": "283",
		"தலப் பெயர்": "பாவநாசத் திருக்குறுந்தொகை",
		"பதிக எண்": "5.099",
		"பாடல்": "பாவமும்பழி பற்றற"
	},
	{
		"வரிசை எண்": "284",
		"தலப் பெயர்": "ஆதிபுராணத் திருக்குறுந்தொகை",
		"பதிக எண்": "5.100",
		"பாடல்": "வேதநாயகன் வேதியர்"
	},
	{
		"வரிசை எண்": "285",
		"தலப் பெயர்": "திருப்புத்தூர்",
		"பதிக எண்": "6.076",
		"பாடல்": "புரிந்தமரர் தொழுதேத்தும்"
	},
	{
		"வரிசை எண்": "286",
		"தலப் பெயர்": "திருஆலவாய்",
		"பதிக எண்": "6.019",
		"பாடல்": "முளைத்தானை எல்லார்க்கும்"
	},
	{
		"வரிசை எண்": "287",
		"தலப் பெயர்": "திருஆலவாய்",
		"பதிக எண்": "4.062",
		"பாடல்": "வேதியாவேத கீதா"
	},
	{
		"வரிசை எண்": "288",
		"தலப் பெயர்": "திருப்பூவணம்",
		"பதிக எண்": "6.018",
		"பாடல்": "வடிவேறு திரிசூலந்"
	},
	{
		"வரிசை எண்": "289",
		"தலப் பெயர்": "திருஇராமேச்சரம்",
		"பதிக எண்": "4.061",
		"பாடல்": "பாசமுங் கழிக்க"
	},
	{
		"வரிசை எண்": "290",
		"தலப் பெயர்": "திருப்புகலூர்",
		"பதிக எண்": "4.016",
		"பாடல்": "செய்யர் வெண்ணூலர்"
	},
	{
		"வரிசை எண்": "291",
		"தலப் பெயர்": "திருப்புகலூர்",
		"பதிக எண்": "4.054",
		"பாடல்": "பகைத்திட்டார் புரங்கள்"
	},
	{
		"வரிசை எண்": "292",
		"தலப் பெயர்": "நின்றத் திருத்தாண்டகம்",
		"பதிக எண்": "6.094",
		"பாடல்": "இருநிலனாய்த் தீயாகி"
	},
	{
		"வரிசை எண்": "293",
		"தலப் பெயர்": "தனித் திருத்தாண்டகம்",
		"பதிக எண்": "6.095",
		"பாடல்": "அப்பன்நீ அம்மைநீ"
	},
	{
		"வரிசை எண்": "294",
		"தலப் பெயர்": "க்ஷேத்திரக்கோவை",
		"பதிக எண்": "6.070",
		"பாடல்": "தில்லைச் சிற்றம்பல"
	},
	{
		"வரிசை எண்": "295",
		"தலப் பெயர்": "குறைந்த நேரிசை",
		"பதிக எண்": "4.078",
		"பாடல்": "வென்றிலேன் புலன்க"
	},
	{
		"வரிசை எண்": "296",
		"தலப் பெயர்": "குறைந்த நேரிசை",
		"பதிக எண்": "4.079",
		"பாடல்": "தம்மானங் காப்ப"
	},
	{
		"வரிசை எண்": "297",
		"தலப் பெயர்": "தனித் திருநேரிசை",
		"பதிக எண்": "4.075",
		"பாடல்": "தொண்டனேன் பட்ட"
	},
	{
		"வரிசை எண்": "298",
		"தலப் பெயர்": "தனித் திருநேரிசை",
		"பதிக எண்": "4.076",
		"பாடல்": "மருளவா மனத்த"
	},
	{
		"வரிசை எண்": "299",
		"தலப் பெயர்": "தனித் திருநேரிசை",
		"பதிக எண்": "4.077",
		"பாடல்": "கடும்பகல் நட்ட"
	},
	{
		"வரிசை எண்": "300",
		"தலப் பெயர்": "ஆருயிர்த் திருவிருத்தம்",
		"பதிக எண்": "4.084",
		"பாடல்": "எட்டாந் திசைக்கும்"
	},
	{
		"வரிசை எண்": "301",
		"தலப் பெயர்": "தசபுராணம்",
		"பதிக எண்": "4.014",
		"பாடல்": "பருவரை யொன்றுசுற்றி"
	},
	{
		"வரிசை எண்": "302",
		"தலப் பெயர்": "பாவநாசத் திருப்பதிகம்",
		"பதிக எண்": "4.015",
		"பாடல்": "பற்றற் றார்சேற்"
	},
	{
		"வரிசை எண்": "303",
		"தலப் பெயர்": "பொது - சிவனெனுமோசை",
		"பதிக எண்": "4.008",
		"பாடல்": "சிவனெனு மோசையல்ல"
	},
	{
		"வரிசை எண்": "304",
		"தலப் பெயர்": "நினைந்த திருநேரிசை",
		"பதிக எண்": "4.074",
		"பாடல்": "முத்தினை மணியைப்"
	},
	{
		"வரிசை எண்": "305",
		"தலப் பெயர்": "வினாவிடைத் திருத்தாண்டகம்",
		"பதிக எண்": "6.097",
		"பாடல்": "அண்டங் கடந்த"
	},
	{
		"வரிசை எண்": "306",
		"தலப் பெயர்": "திருஆரூர்",
		"பதிக எண்": "6.027",
		"பாடல்": "பொய்ம்மாயப் பெருங்"
	},
	{
		"வரிசை எண்": "307",
		"தலப் பெயர்": "திருப்புகலூர்",
		"பதிக எண்": "4.105",
		"பாடல்": "தன்னைச் சரணென்று"
	},
	{
		"வரிசை எண்": "308",
		"தலப் பெயர்": "பசுபதித் திருவிருத்தம்",
		"பதிக எண்": "4.110",
		"பாடல்": "சாம்பலைப் பூசித்"
	},
	{
		"வரிசை எண்": "309",
		"தலப் பெயர்": "சரக்கறை திருவிருத்தம்",
		"பதிக எண்": "4.111",
		"பாடல்": "விடையும் விடைப்"
	},
	{
		"வரிசை எண்": "310",
		"தலப் பெயர்": "தனித் திருவிருத்தம்",
		"பதிக எண்": "4.112",
		"பாடல்": "வெள்ளிக் குழைத்துணி"
	},
	{
		"வரிசை எண்": "311",
		"தலப் பெயர்": "தனித் திருவிருத்தம்",
		"பதிக எண்": "4.113",
		"பாடல்": "பவளத் தடவரை"
	},
	{
		"வரிசை எண்": "312",
		"தலப் பெயர்": "திருப்புகலூர்",
		"பதிக எண்": "6.099",
		"பாடல்": "எண்ணுகேன் என்சொல்லி"
	}
]
